pyslvs_ui/__init__.py
pyslvs_ui/__main__.py
pyslvs_ui/py.typed
pyslvs_ui/qt_patch.py
pyslvs_ui/entities/__init__.py
pyslvs_ui/entities/edit_link.py
pyslvs_ui/entities/edit_link_ui.py
pyslvs_ui/entities/edit_point.py
pyslvs_ui/entities/edit_point_ui.py
pyslvs_ui/entities/relocate_point.py
pyslvs_ui/entities/relocate_point_ui.py
pyslvs_ui/entities/utility.py
pyslvs_ui/graphics/__init__.py
pyslvs_ui/graphics/canvas.py
pyslvs_ui/graphics/chart.py
pyslvs_ui/graphics/color.py
pyslvs_ui/graphics/nx_layout.py
pyslvs_ui/graphics/path_parser.py
pyslvs_ui/icons/aim.png
pyslvs_ui/icons/arrow_down.png
pyslvs_ui/icons/arrow_up.png
pyslvs_ui/icons/bearing.png
pyslvs_ui/icons/calculator.png
pyslvs_ui/icons/capture.png
pyslvs_ui/icons/clean.png
pyslvs_ui/icons/collections.png
pyslvs_ui/icons/configure.png
pyslvs_ui/icons/conflict.png
pyslvs_ui/icons/connect.png
pyslvs_ui/icons/copy.png
pyslvs_ui/icons/data.png
pyslvs_ui/icons/data_update.png
pyslvs_ui/icons/delete.png
pyslvs_ui/icons/dimensional_synthesis.png
pyslvs_ui/icons/disconnect.png
pyslvs_ui/icons/dxf.png
pyslvs_ui/icons/edges_to_atlas.png
pyslvs_ui/icons/example.png
pyslvs_ui/icons/excel.png
pyslvs_ui/icons/exit.png
pyslvs_ui/icons/fitting.png
pyslvs_ui/icons/formula.png
pyslvs_ui/icons/free_move_off.png
pyslvs_ui/icons/fullscreen.png
pyslvs_ui/icons/github.png
pyslvs_ui/icons/grid.png
pyslvs_ui/icons/guide.png
pyslvs_ui/icons/history.png
pyslvs_ui/icons/horizontal_align.png
pyslvs_ui/icons/id.png
pyslvs_ui/icons/interrupted.png
pyslvs_ui/icons/kmol.png
pyslvs_ui/icons/konsole.png
pyslvs_ui/icons/link.png
pyslvs_ui/icons/loadfile.png
pyslvs_ui/icons/main.icns
pyslvs_ui/icons/main.ico
pyslvs_ui/icons/main.pdn
pyslvs_ui/icons/main.png
pyslvs_ui/icons/mechanism.png
pyslvs_ui/icons/merge.png
pyslvs_ui/icons/merge_from.png
pyslvs_ui/icons/motor.png
pyslvs_ui/icons/new_file.png
pyslvs_ui/icons/new_window.png
pyslvs_ui/icons/normal_size.png
pyslvs_ui/icons/normalization.png
pyslvs_ui/icons/number.png
pyslvs_ui/icons/paste.png
pyslvs_ui-22.7.0.dist-info/LICENSE
pyslvs_ui-22.7.0.dist-info/METADATA
pyslvs_ui-22.7.0.dist-info/WHEEL
pyslvs_ui-22.7.0.dist-info/entry_points.txt
pyslvs_ui-22.7.0.dist-info/top_level.txt
pyslvs_ui-22.7.0.dist-info/RECORD
