Metadata-Version: 2.1
Name: pyslvs-ui
Version: 22.7.0
Summary: An open source planar linkage mechanism simulation and mechanical synthesis system.
Home-page: https://github.com/KmolYuan/Pyslvs-UI
Author: Yuan Chang
Author-email: pyslvs@gmail.com
License: AGPL
Keywords: pyslvs,pyqt5,gui,mechanical-engineering,2d
Classifier: Programming Language :: Python :: 3.8
Classifier: Programming Language :: Python :: 3.9
Classifier: Programming Language :: Python :: 3.10
Classifier: Environment :: X11 Applications :: Qt
Classifier: Topic :: Scientific/Engineering
Classifier: License :: OSI Approved :: GNU Affero General Public License v3 or later (AGPLv3+)
Classifier: Operating System :: OS Independent
Classifier: Typing :: Typed
Requires-Python: >=3.8
License-File: LICENSE
Requires-Dist: requests
Requires-Dist: qtpy
Requires-Dist: pyqt5
Requires-Dist: ezdxf
Requires-Dist: numpy
Requires-Dist: matplotlib
Requires-Dist: openpyxl
Requires-Dist: lark-parser
Requires-Dist: pyyaml
Requires-Dist: qrcode
Requires-Dist: pyslvs
Provides-Extra: slvs
Requires-Dist: python-solvespace ; extra == 'slvs'
Provides-Extra: splev
Requires-Dist: scipy ; extra == 'splev'
